ospyata/__init__.py
ospyata/__version__.py
ospyata/osmata.py
ospyata-3.1.3.dist-info/LICENSE
ospyata-3.1.3.dist-info/METADATA
ospyata-3.1.3.dist-info/WHEEL
ospyata-3.1.3.dist-info/top_level.txt
ospyata-3.1.3.dist-info/RECORD
