Metadata-Version: 2.1
Name: ospyata
Version: 3.1.3
Summary: Python library for the open source bookmark app Osmata.
Home-page: https://github.com/aerocyber/ospyata
Author: aerocyber
License: MIT License
Project-URL: Bug Reports, https://github.com/aerocyber/ospyata/issues
Project-URL: Source, https://github.com/aerocyber/ospyata/
Keywords: osmata,development,osmata-bindings,osmata-python-bindings,bookmarks,ospyata
Classifier: Development Status :: 5 - Production/Stable
Classifier: Intended Audience :: Developers
Classifier: License :: OSI Approved :: MIT License
Classifier: Programming Language :: Python :: 3
Classifier: Programming Language :: Python :: 3.11
Classifier: Programming Language :: Python :: 3 :: Only
Requires-Python: >=3.11, <4
License-File: LICENSE
